rocket/__init__.py
rocket/rocket.py
rocket_sba22-0.1.0.dist-info/LICENSE.txt
rocket_sba22-0.1.0.dist-info/METADATA
rocket_sba22-0.1.0.dist-info/WHEEL
rocket_sba22-0.1.0.dist-info/top_level.txt
rocket_sba22-0.1.0.dist-info/RECORD
