Metadata-Version: 2.1
Name: rocket_sba22
Version: 0.1.0
Summary: A package for simulating rockets and shuttles
Home-page: https://github.com/SenhadjiMSaid
Author: Ali abbou oussama
Author-email: o.aliabbou@esi-sba.com
License: MIT
Classifier: Programming Language :: Python :: 3
Classifier: License :: OSI Approved :: MIT License
Classifier: Operating System :: OS Independent
Requires-Python: >=3.6
License-File: LICENSE.txt
